{"per_page":10,"total":9,"current":1,"data":[{"year":"2022","months":[{"month":"1月","entries":[{"title":"Macbook优化","date":"2022-01-19T12:44:01.000Z","date_formatted":{"ll":"2022年1月19日","L":"2022/01/19","MM-DD":"01-19"},"link":"posts/3c3fd7cd"},{"title":"用pmset管理macOS的睡眠","date":"2022-01-19T12:44:01.000Z","date_formatted":{"ll":"2022年1月19日","L":"2022/01/19","MM-DD":"01-19"},"link":"posts/3c3fd7cd"},{"title":"解决github图片加载不出来","date":"2022-01-15T10:37:25.000Z","date_formatted":{"ll":"2022年1月15日","L":"2022/01/15","MM-DD":"01-15"},"link":"posts/7cd4f2fa"},{"title":"mac版ghub安装完成后卡登陆界面","date":"2022-01-15T06:14:28.000Z","date_formatted":{"ll":"2022年1月15日","L":"2022/01/15","MM-DD":"01-15"},"link":"posts/25da7a66"}]}]},{"year":"2021","months":[{"month":"12月","entries":[{"title":"Js","date":"2021-12-31T12:35:52.000Z","date_formatted":{"ll":"2021年12月31日","L":"2021/12/31","MM-DD":"12-31"},"link":"posts/824395f6"},{"title":"JavaWeb","date":"2021-12-31T12:35:52.000Z","date_formatted":{"ll":"2021年12月31日","L":"2021/12/31","MM-DD":"12-31"},"link":"posts/99720b1c"},{"title":"Java","date":"2021-12-31T12:35:52.000Z","date_formatted":{"ll":"2021年12月31日","L":"2021/12/31","MM-DD":"12-31"},"link":"posts/df2849ec"}]},{"month":"5月","entries":[{"title":"python考试","date":"2021-05-31T11:54:43.000Z","date_formatted":{"ll":"2021年5月31日","L":"2021/05/31","MM-DD":"05-31"},"link":"posts/aabdde41"},{"title":"穿越机配置单","date":"2021-05-18T12:30:07.000Z","date_formatted":{"ll":"2021年5月18日","L":"2021/05/18","MM-DD":"05-18"},"link":"posts/f65c706c"},{"title":"穿越机详解","date":"2021-05-18T12:29:56.000Z","date_formatted":{"ll":"2021年5月18日","L":"2021/05/18","MM-DD":"05-18"},"link":"posts/f4c753e8"}]}]}]}